Metadata-Version: 1.0
Name: Normal-Binomial-dist
Version: 1.1
Summary: Gaussian distributions
Home-page: UNKNOWN
Author: Pranav
Author-email: UNKNOWN
License: UNKNOWN
Platform: UNKNOWN
